bcraapi/__init__.py
bcraapi/centraldeudores.py
bcraapi/cheques.py
bcraapi/estadisticas.py
bcraapi/estadisticascambiarias.py
bcraapi/cert/bcra.gob.ar.crt
bcraapi-3.0.0.dist-info/licenses/LICENSE
bcraapi-3.0.0.dist-info/METADATA
bcraapi-3.0.0.dist-info/WHEEL
bcraapi-3.0.0.dist-info/top_level.txt
bcraapi-3.0.0.dist-info/RECORD
